apres/__init__.py
apres/libapres_manylinux2014_armv7l.so
apres/libapres_manylinux2014_x86_64.so
apres-0.3.23.dist-info/LICENSE
apres-0.3.23.dist-info/METADATA
apres-0.3.23.dist-info/WHEEL
apres-0.3.23.dist-info/top_level.txt
apres-0.3.23.dist-info/RECORD
