Metadata-Version: 2.1
Name: apres
Version: 0.3.23
Summary: External bindings for apres MIDI library
Home-page: https://burnsomni.net/git/apres
Author: Quintin Smith
Author-email: smith.quintin@protonmail.com
License: UNKNOWN
Platform: UNKNOWN
Classifier: Programming Language :: Python :: 3
Classifier: Programming Language :: Rust
Classifier: License :: OSI Approved :: GNU General Public License v2 or later (GPLv2+)
Classifier: Operating System :: POSIX :: Linux
Requires-Python: >=3.7
License-File: LICENSE
Requires-Dist: cffi
